<?xml version="1.0" encoding="UTF-8"?>
<beans xmlns="http://www.springframework.org/schema/beans"
	xmlns:xsi="http://www.w3.org/2001/XMLSchema-instance"
	xsi:schemaLocation="http://www.springframework.org/schema/beans http://www.springframework.org/schema/beans/spring-beans.xsd">
	
	<!-- Root Context: defines shared resources visible to all other web components -->
	
	<bean id="dataSource"
		class="org.springframework.jdbc.datasource.DriverManagerDataSource">
		<property name="driverClassName" value="com.mysql.jdbc.Driver"></property>
		<property name="url" value="jdbc:mysql://localhost:5036/springboard"></property>
		<property name="username" value="root"></property>
		<property name="password" value="0430"></property>
	</bean>
	
	<bean id="sqlSessionFactory"
		class="org.mybatis.spring.SqlSessionFactoryBean">
		<property name="dataSource" ref="dataSource"></property>
		<property name="configLocation" value="classpath:config/mybatis-config.xml"></property>
		<property name="mapperLocations" value="classpath:mapper/boardMapper.xml"></property>
	</bean>
	
	<bean id="transactionManger"
		class="org.springframework.jdbc.datasource.DataSourceTransactionManager">
		<property name="dataSource" ref="dataSource"></property>	
	</bean>
	
	<bean id="sqlSession"
		class="org.mybatis.spring.SqlSessionTemplate">
		<constructor-arg ref="sqlSessionFactory"></constructor-arg>	
	</bean>
</beans>
